viralqc/__init__.py
viralqc/cli.py
viralqc/config/datasets.yml
viralqc/core/__init__.py
viralqc/core/datasets.py
viralqc/core/defaults.py
viralqc/core/errors.py
viralqc/core/models.py
viralqc/core/run_analysis.py
viralqc/core/utils.py
viralqc/scripts/__init__.py
viralqc/scripts/get_blast_database.smk
viralqc/scripts/get_public_datasets.smk
viralqc/scripts/run_analysis.smk
viralqc/scripts/python/__init__.py
viralqc/scripts/python/blast_wrapper.py
viralqc/scripts/python/extract_target_regions.py
viralqc/scripts/python/format_nextclade_sort.py
viralqc/scripts/python/get_github_dataset.py
viralqc/scripts/python/get_minimizer_index.py
viralqc/scripts/python/jsonl_to_gff.py
viralqc/scripts/python/post_process_nextclade.py
viralqc/scripts/python/reorder_cds.py
viralqc-0.13.0.dist-info/METADATA
viralqc-0.13.0.dist-info/WHEEL
viralqc-0.13.0.dist-info/entry_points.txt
viralqc-0.13.0.dist-info/licenses/LICENSE
viralqc-0.13.0.dist-info/RECORD
