Metadata-Version: 2.4
Name: viralQC
Version: 0.13.0
Summary: A tool and package for quality control of consensus virus genomes.
Project-URL: Homepage, https://github.com/InstitutoTodosPelaSaude/viralQC
Author-email: Filipe Zimmer Dezordi <zimmer.filipe@gmail.com>
License: MIT
License-File: LICENSE
Keywords: python,quality-control,snakemake,virus
Classifier: Development Status :: 3 - Alpha
Classifier: Intended Audience :: Science/Research
Classifier: License :: OSI Approved :: MIT License
Classifier: Operating System :: OS Independent
Classifier: Programming Language :: Python :: 3
Classifier: Topic :: Software Development :: Libraries :: Python Modules
Classifier: Topic :: Utilities
Requires-Python: <3.12,>=3.8
Requires-Dist: biopython==1.86
Requires-Dist: colorlog>=6.3
Requires-Dist: pandas>=2.2
Requires-Dist: python-multipart==0.0.20
Requires-Dist: pyyaml>=6.0
Requires-Dist: typer>=0.16
Provides-Extra: cli
Requires-Dist: colorlog>=6.3; extra == 'cli'
Requires-Dist: typer>=0.16; extra == 'cli'
Provides-Extra: dev
Requires-Dist: black>=24.3; extra == 'dev'
Requires-Dist: pytest>=8.0; extra == 'dev'
